myacme/__init__.py
myacme/__main__.py
myacme/client.py
myacme/extras/zonefile.py
myacme-0.1.1.dist-info/LICENSE
myacme-0.1.1.dist-info/METADATA
myacme-0.1.1.dist-info/WHEEL
myacme-0.1.1.dist-info/entry_points.txt
myacme-0.1.1.dist-info/top_level.txt
myacme-0.1.1.dist-info/RECORD
