Metadata-Version: 2.1
Name: myacme
Version: 0.1.1
Summary: MyACME client library and command line tool
Home-page: https://declassed.art/repository/myacme
Author: AXY
Author-email: axy@declassed.art
License: UNKNOWN
Platform: UNKNOWN
Classifier: Programming Language :: Python :: 3
Classifier: License :: OSI Approved :: BSD License
Classifier: Operating System :: OS Independent
Classifier: Environment :: Console
Classifier: Intended Audience :: Developers
Classifier: Intended Audience :: System Administrators
Classifier: Topic :: Internet :: WWW/HTTP
Classifier: Topic :: Utilities
Classifier: Development Status :: 4 - Beta
Requires-Python: >=3.7
License-File: LICENSE
Requires-Dist: atomicwrites
Requires-Dist: cryptography (>=3.1)
Requires-Dist: idna
Requires-Dist: kvgargs
Requires-Dist: pyyaml
Requires-Dist: requests
